unitxt/__init__.py
unitxt/api.py
unitxt/artifact.py
unitxt/augmentors.py
unitxt/benchmark.py
unitxt/blocks.py
unitxt/card.py
unitxt/catalog.py
unitxt/collections.py
unitxt/collections_operators.py
unitxt/dataclass.py
unitxt/dataset.py
unitxt/dataset_utils.py
unitxt/deprecation_utils.py
unitxt/dialog_operators.py
unitxt/dict_utils.py
unitxt/error_utils.py
unitxt/eval_utils.py
unitxt/file_utils.py
unitxt/formats.py
unitxt/fusion.py
unitxt/generator_utils.py
unitxt/hf_utils.py
unitxt/image_operators.py
unitxt/inference.py
unitxt/instructions.py
unitxt/llm_as_judge.py
unitxt/llm_as_judge_chat_templates.py
unitxt/llm_as_judge_constants.py
unitxt/llm_as_judge_from_template.py
unitxt/llm_as_judge_operators.py
unitxt/llm_as_judge_utils.py
unitxt/loaders.py
unitxt/logging_utils.py
unitxt/metric.py
unitxt/metric_utils.py
unitxt/metrics.py
unitxt/normalizers.py
unitxt/operator.py
unitxt/operators.py
unitxt/parsing_utils.py
unitxt/processors.py
unitxt/random_utils.py
unitxt/recipe.py
unitxt/register.py
unitxt/schema.py
unitxt/serializers.py
unitxt/settings_utils.py
unitxt/span_lableing_operators.py
unitxt/split_utils.py
unitxt/splitters.py
unitxt/standard.py
unitxt/stream.py
unitxt/stream_operators.py
unitxt/string_operators.py
unitxt/struct_data_operators.py
unitxt/system_prompts.py
unitxt/task.py
unitxt/templates.py
unitxt/text_utils.py
unitxt/type_utils.py
unitxt/types.py
unitxt/utils.py
unitxt/validate.py
unitxt/version.py
unitxt/catalog/augmentors/augment_whitespace_prefix_and_suffix_task_input.json
unitxt/catalog/augmentors/augment_whitespace_task_input.json
unitxt/catalog/augmentors/no_augmentation.json
unitxt/catalog/augmentors/image/grey_scale.json
unitxt/catalog/augmentors/image/grid_lines.json
unitxt/catalog/augmentors/image/oldify.json
unitxt/catalog/augmentors/image/white_noise.json
unitxt/catalog/augmentors/table/duplicate_columns.json
unitxt/catalog/augmentors/table/duplicate_rows.json
unitxt/catalog/augmentors/table/insert_empty_rows.json
unitxt-1.16.4.dist-info/LICENSE
unitxt-1.16.4.dist-info/METADATA
unitxt-1.16.4.dist-info/WHEEL
unitxt-1.16.4.dist-info/entry_points.txt
unitxt-1.16.4.dist-info/top_level.txt
unitxt-1.16.4.dist-info/RECORD
