Metadata-Version: 2.1
Name: unitxt
Version: 1.16.4
Summary: Load any mixture of text to text data in one line of code
Author-email: IBM Research <elron.bandel@ibm.com>
License:                                  Apache License
Project-URL: Homepage, https://www.unitxt.ai
Project-URL: Documentation, https://www.unitxt.ai/en/latest/documentation.html
Project-URL: Repository, https://github.com/ibm/unitxt
Classifier: Programming Language :: Python :: 3
Classifier: Operating System :: OS Independent
Requires-Python: >=3.8
License-File: LICENSE
Requires-Dist: datasets>=2.16.0
Requires-Dist: evaluate
Requires-Dist: absl-py
Requires-Dist: ipadic
Requires-Dist: scipy
Provides-Extra: dev
Requires-Dist: ruff; extra == "dev"
Requires-Dist: pre-commit; extra == "dev"
Requires-Dist: detect-secrets; extra == "dev"
Requires-Dist: tomli; extra == "dev"
Requires-Dist: codespell; extra == "dev"
Requires-Dist: fuzzywuzzy; extra == "dev"
Requires-Dist: httpretty; extra == "dev"
Provides-Extra: docs
Requires-Dist: sphinx_rtd_theme; extra == "docs"
Requires-Dist: piccolo_theme; extra == "docs"
Requires-Dist: sphinxext-opengraph; extra == "docs"
Requires-Dist: datasets; extra == "docs"
Requires-Dist: evaluate; extra == "docs"
Requires-Dist: nltk; extra == "docs"
Requires-Dist: sacrebleu; extra == "docs"
Requires-Dist: absl-py; extra == "docs"
Requires-Dist: rouge_score; extra == "docs"
Requires-Dist: scikit-learn; extra == "docs"
Requires-Dist: jiwer; extra == "docs"
Requires-Dist: editdistance; extra == "docs"
Requires-Dist: fuzzywuzzy; extra == "docs"
Provides-Extra: helm
Requires-Dist: crfm-helm[unitxt]>=0.5.3; extra == "helm"
Provides-Extra: service
Requires-Dist: torch==1.12.1; extra == "service"
Requires-Dist: fastapi==0.109.0; extra == "service"
Requires-Dist: uvicorn[standard]==0.27.0.post1; extra == "service"
Requires-Dist: python-jose[cryptography]==3.3.0; extra == "service"
Requires-Dist: transformers; extra == "service"
Provides-Extra: tests
Requires-Dist: bert_score; extra == "tests"
Requires-Dist: transformers; extra == "tests"
Requires-Dist: sentence_transformers; extra == "tests"
Requires-Dist: ibm-cos-sdk; extra == "tests"
Requires-Dist: kaggle==1.6.14; extra == "tests"
Requires-Dist: opendatasets; extra == "tests"
Requires-Dist: httpretty~=1.1.4; extra == "tests"
Requires-Dist: editdistance; extra == "tests"
Requires-Dist: rouge-score; extra == "tests"
Requires-Dist: nltk; extra == "tests"
Requires-Dist: mecab-python3; extra == "tests"
Requires-Dist: sacrebleu[ko]; extra == "tests"
Requires-Dist: scikit-learn<=1.5.2; extra == "tests"
Requires-Dist: jiwer; extra == "tests"
Requires-Dist: conllu; extra == "tests"
Requires-Dist: llama-index-core; extra == "tests"
Requires-Dist: llama-index-llms-openai; extra == "tests"
Requires-Dist: pytrec-eval; extra == "tests"
Requires-Dist: SentencePiece; extra == "tests"
Requires-Dist: fuzzywuzzy; extra == "tests"
Requires-Dist: openai; extra == "tests"
Requires-Dist: ibm-generative-ai; extra == "tests"
Requires-Dist: bs4; extra == "tests"
Requires-Dist: tenacity==8.3.0; extra == "tests"
Requires-Dist: accelerate; extra == "tests"
Requires-Dist: spacy; extra == "tests"
Requires-Dist: Wikipedia-API; extra == "tests"
Provides-Extra: ui
Requires-Dist: gradio; extra == "ui"
Requires-Dist: transformers; extra == "ui"
Provides-Extra: watsonx
Requires-Dist: ibm-watsonx-ai==1.1.14; extra == "watsonx"
Provides-Extra: inference-tests
Requires-Dist: litellm==v1.52.9; extra == "inference-tests"
Requires-Dist: tenacity; extra == "inference-tests"
Requires-Dist: diskcache; extra == "inference-tests"
Requires-Dist: numpy==1.26.4; extra == "inference-tests"
Provides-Extra: all
Requires-Dist: unitxt[base]; extra == "all"
Requires-Dist: unitxt[dev]; extra == "all"
Requires-Dist: unitxt[docs]; extra == "all"
Requires-Dist: unitxt[helm]; extra == "all"
Requires-Dist: unitxt[service]; extra == "all"
Requires-Dist: unitxt[tests]; extra == "all"
Requires-Dist: unitxt[ui]; extra == "all"
Requires-Dist: unitxt[watsonx]; extra == "all"
